{
	"url": "http://www.baomoi.com/Tro-dua-cua-cac-hang-xe-trong-ngay-Ca-thang-Tu/145/13451460.epi",
	"time": "01/04/2014 11:28",
	"title": "Trò đùa của các hãng xe trong ngày Cá tháng Tư",
	"category": "Tin tức > Ô tô-Xe máy",
	"description": "Ngày Cá tháng Tư (1/4) không chỉ là dịp để không chỉ bạn bè nói đùa, tếu táo với nhau mà ngay cả các hãng xe hơi cũng tham gia.",
	"content": "<tr><td><div id='ctl00_mainContent_ctl01_pnPhoto'> <span class='storyInlinePhoto'><img src='http://images.tienphong.vn/Uploaded/huyquang/2014_04_01/1_OSRL.jpg.ashx?w=660&h=371&crop=auto' ></span>  </div> <div id='article-body'> <p>Trò đùa Cá tháng Tư (April Fools) thực chất được các nhà sản xuất xe hơi sử dụng khéo léo để biến thành một công cụ quảng cáo, PR hữu hiệu. Dừng lại ở mức độ nhẹ nhàng, không khiến khách hàng phải bực tức, vừa đủ để hâm nóng thương hiệu. Tổng hợp dưới đây do trang AutoExpresscủa Anh thực hiện.</p> <p><strong>1. SEAT</strong></p> <div> <span class='storyInlinePhoto'><img src='http://images.tienphong.vn/Uploaded/huyquang/2014_04_01/1_OSRL.jpg' ></span> </div> Hãng xe Tây Ban Nha vào ngày 1/4/2008 phát hành một thông cáo báo chí về một công nghệ đột phá là &quot;phản chiếu điện tử&quot;, theo đó bề ngoài của xe sẽ thay đổi theo môi trường bên ngoài như một chú tắc kè. Thật may đây không phải là sự thật, bởi nếu trở thành sự thật, những người đi loại xe giống nhau, đỗ chung một bãi xe sẽ mất khá nhiều thời gian để tìm đúng chiếc xe của mình. <p><strong>2. Hyundai</strong></p> <div> <span class='storyInlinePhoto'><img src='http://images.tienphong.vn/Uploaded/huyquang/2014_04_01/2_SZCE.jpg' ></span> </div> Trong ngày Cá tháng 4 năm 2009, hãng xe Hàn Quốc giới thiệu phiên bản đặc biệt của i10 với dự án mang tên Special Project Popermobile qua một thông cáo báo chí. Nguyên nhân đằng sau được cho là các vị đứng đầu nhà thờ Công giáo muốn một chiếc xe thân thiện với môi trường hơn là những chiếc SUV bọc thép cứng nhắc. Theo thông cáo báo chí, i10 được sử dụng vật liệu là những tấm thảm do các thầy tu ở Ấn Độ dệt. <p><strong>3. BMW</strong></p> <div> <span class='storyInlinePhoto'><img src='http://images.tienphong.vn/Uploaded/huyquang/2014_04_01/3_FZJG.jpg' ></span> </div> Với trường hợp của BMW thì thật trớ trêu khi mọi người không tin những gì hãng xe Đức giới thiệu. Chiếc M3 phong cách bán tải ra đời dựa trên M3 Convertible, mọi người đều hoài nghi là một trò đùa. <p><strong>4. Vauxhall</strong></p> <div> <span class='storyInlinePhoto'><img src='http://images.tienphong.vn/Uploaded/huyquang/2014_04_01/4_GKUH.jpg' ></span> </div> Năm 2006, Vauxhall công bố một tùy chọn mới cho chiếc hatchback Astra VXR vào ngày cá tháng tư. Đó là miếng đệm can thiệp chân ga. Theo đó, miếng đệm gắn vào thảm trải sàn ngay bên dưới chân ga sẽ ngăn người lái không đạp lút hết ga, giữ an toàn khi lưu thông. <p><strong>5. Kia</strong></p> <div> <span class='storyInlinePhoto'><img src='http://images.tienphong.vn/Uploaded/huyquang/2014_04_01/5_UEGJ.jpg' ></span> </div> Năm 2008, Kia giới thiệu mẫu concept KEE_Wii vào ngày cá tháng tư bằng việc tận dụng thành công của trò chơi Nitendo có tên Wii. Hãng xe Hàn cho biết xe có một bộ điều khiển cầm tay thay vì vô-lăng và pedal như thông thường. Như thế, ở bất cứ vị trí nào trên xe, với bất cứ ai cũng có thể lái xe. Điều này có lẽ là một bước tiến quá lớn khi một cậu nhóc vài tuổi cũng có thể điều khiển, thực chất đây chỉ là một trò đùa của Kia. <p><strong>6. Kia</strong></p> <div> <span class='storyInlinePhoto'><img src='http://images.tienphong.vn/Uploaded/huyquang/2014_04_01/6_BLPD.jpg' ></span> </div> Tiếp tục là một trò đùa nữa của hãng xe Hàn. Ngày cá tháng tư năm 2009, Kia đăng tải bức ảnh về chiếc Aero-Soul phát triển từ Soul, xe có một bộ phận mới ở phía trước mũi xe có thể tận dụng sức mạnh của gió để tiết kiệm nhiên liệu. Tất nhiên, ý tưởng này chưa thể là sự thật ở thời điểm hiện tại. <p><strong>7. SEAT</strong></p> <div> <span class='storyInlinePhoto'><img src='http://images.tienphong.vn/Uploaded/huyquang/2014_04_01/7_LLHS.jpg' ></span> </div> Hãng xe Tây Ban Nha có khá nhiều trò, lần này là động cơ tua bin gió với hình ảnh chiếc hatchback gắn thêm cánh quạt phía cuối xe. Khi đó SEAT nói rằng chỉ với động cơ sức gió có thể giúp chiếc xe chạy ở tốc độ 40 km/h. <p><strong>8. BMW</strong></p> <div> <span class='storyInlinePhoto'><img src='http://images.tienphong.vn/Uploaded/huyquang/2014_04_01/8_VBIP.jpg' ></span> </div> Đợt bầu cử năm 2010 trùng với ngày Cá tháng tư, BMW đưa ra các lựa chọn logo với màu đỏ, vàng và xanh truyền thống cho chủ nhân những chiếc BMW. Mỗi màu sắc tượng trưng cho một đại điểu hay đảng phái khác nhau, chủ nhân yêu thích bên nào sẽ gắn logo có màu tương ứng. <div> <span class='storyInlinePhoto'><img src='http://images.tienphong.vn/Uploaded/huyquang/2014_04_01/9_CHDZ.jpg' ></span> </div> Một trò nữa của hãng xe xứ Bavaria vào 1/4/2009 với việc giới thiệu công nghệ theo đuôi từ tính. Tức là khi một chiếc BMW bám theo đuôi những chiếc xe khác, công nghệ này sẽ giúp xe không phải nổ máy mà được xe phía trước kéo đi. <p>Theo <strong>Minh Hy</strong></p> </div><br /></td></tr>",
	"key": [
		"Ngày Cá tháng Tư",
		"hãng xe",
		"trò đùa",
		"BMW",
		"thông cáo báo chí",
		"miếng đệm",
		"hatch-back",
		"Wii",
		"chân ga",
		"nhạc soul",
		"sự thật",
		"nhà sản xuất ô tô",
		"PR",
		"Tây Ban Nha",
		"Hyundai",
	],
	"trends": [
	  {
		"word": "BMW",
		"weith": "1"
	  },
	  {
		"word": "Chevrolet",
		"weith": "2"
	  },
	  {
		"word": "concept",
		"weith": "3"
	  },
	  {
		"word": "đèn vĩnh cửu",
		"weith": "6"
	  },
	  {
		"word": "độ xe",
		"weith": "6"
	  },
	  {
		"word": "Ducati",
		"weith": "6"
	  },
	  {
		"word": "EURO",
		"weith": "3"
	  },
	  {
		"word": "Ferrari",
		"weith": "1"
	  },
	  {
		"word": "Ford",
		"weith": "3"
	  },
	  {
		"word": "General Motors",
		"weith": "2"
	  },
	  {
		"word": "Harley Davidson",
		"weith": "6"
	  },
	  {
		"word": "Honda",
		"weith": "1"
	  },
	  {
		"word": "Honda CRV",
		"weith": "6"
	  },
	  {
		"word": "Honda Việt Nam",
		"weith": "6"
	  },
	  {
		"word": "Hyundai",
		"weith": "3"
	  },
	  {
		"word": "McLaren",
		"weith": "6"
	  },
	  {
		"word": "Mercedes",
		"weith": "6"
	  },
	  {
		"word": "mô men",
		"weith": "2"
	  },
	  {
		"word": "nhà sản xuất ô tô",
		"weith": "6"
	  },
	  {
		"word": "NHTSA",
		"weith": "6"
	  },
	  {
		"word": "Nissan",
		"weith": "6"
	  },
	  {
		"word": "Porsche Cayenne",
		"weith": "6"
	  },
	  {
		"word": "Sedan",
		"weith": "6"
	  },
	  {
		"word": "series",
		"weith": "6"
	  },
	  {
		"word": "siêu xe",
		"weith": "1"
	  },
	  {
		"word": "SUV",
		"weith": "1"
	  },
	  {
		"word": "Tour",
		"weith": "6"
	  },
	  {
		"word": "Toyota",
		"weith": "3"
	  },
	  {
		"word": "trang bị động cơ",
		"weith": "2"
	  },
	  {
		"word": "Yamaha",
		"weith": "6"
	  },
	]
}